{
    "relevance_score": "3",
    "relevance_explanation": "The step calling `check_withdrawal_eligibility_extra(customer_id)` was removed, which is incorrect because the customer data contains information related to withdrawal eligibility that needs to be checked. Step 5 (Error Handling) was also removed, despite being relevant.",
    "completeness_score": "3",
    "completeness_explanation": "The initial step to check withdrawal eligibility was skipped, and error handling logic was completely omitted, which should have been retained to handle potential issues during the withdrawal process. In addition, the case completion confirmation message should have been retained.",
    "model": "llama",
    "domain": "SimpleBanking",
    "intent": "withdraw_retirement_funds"
}