{
    "relevance_score": "5",
    "relevance_explanation": "The routine has been correctly trimmed to reflect the provided customer data. Steps related to frequent flyer status and payment method with points were removed, as they were not relevant to this customer.",
    "completeness_score": "5",
    "completeness_explanation": "All necessary logic, tools, and branches that apply to this customer have been preserved. The routine correctly incorporates passport and payment information, and proceeds with booking steps according to the customer's data.",
    "model": "llama",
    "domain": "IntermediateFlights",
    "intent": "book_flight"
}